django_multi_email_field-0.8.0.dist-info/licenses/LICENSE
multi_email_field/__init__.py
multi_email_field/fields.py
multi_email_field/forms.py
multi_email_field/models.py
multi_email_field/widgets.py
multi_email_field/tests/__init__.py
multi_email_field/tests/models.py
multi_email_field/tests/tests.py
django_multi_email_field-0.8.0.dist-info/METADATA
django_multi_email_field-0.8.0.dist-info/WHEEL
django_multi_email_field-0.8.0.dist-info/top_level.txt
django_multi_email_field-0.8.0.dist-info/RECORD
